LICENSE
setup.cfg
setup.py
google_images_hunter/__init__.py
google_images_hunter/example.py
google_images_hunter/google_images_hunter.py
google_images_hunter/image_downloader.py
google_images_hunter.egg-info/PKG-INFO
google_images_hunter.egg-info/SOURCES.txt
google_images_hunter.egg-info/dependency_links.txt
google_images_hunter.egg-info/requires.txt
google_images_hunter.egg-info/top_level.txt